imgInfo/__init__.py
imgInfo/main.py
imgInfo-0.4.dist-info/LICENSE
imgInfo-0.4.dist-info/METADATA
imgInfo-0.4.dist-info/WHEEL
imgInfo-0.4.dist-info/entry_points.txt
imgInfo-0.4.dist-info/top_level.txt
imgInfo-0.4.dist-info/RECORD
